[
	{
		"name": "Монополия",
		"players": [2, 3, 4],
		"type": "strategy",
		"description": "Экономическая стратегия, где нужно покупать и продавать недвижимость."
	},
	{
		"name": "Уно",
		"players": [2, 3, 4, 5],
		"type": "party",
		"description": "Простая карточная игра, где нужно избавиться от всех карт."
	},
	{
		"name": "Каркассон",
		"players": [4],
		"type": "strategy",
		"description": "Построение городов и дорог в средневековой тематике."
	},
	{
		"name": "Катан",
		"players": [3, 4],
		"type": "strategy",
		"description": "Настольная игра о заселении острова."
	},
	{
		"name": "Диксит",
		"players": [3, 4],
		"type": "party",
		"description": "Игра ассоциаций с красивыми иллюстрациями."
	},
	{
		"name": "Мафия",
		"players": [4, 5],
		"type": "party",
		"description": "Ролевая игра с поиском мафиози среди игроков."
	},
	{
		"name": "Сплённые истории",
		"players": [2, 3],
		"type": "cooperative",
		"description": "Кооперативная игра с интересными сценариями."
	},
	{
		"name": "Пандемия",
		"players": [2, 3],
		"type": "cooperative",
		"description": "Спасение мира от глобальных эпидемий."
	},
	{
		"name": "Активити",
		"players": [2, 3, 4, 5],
		"type": "family",
		"description": "Игра на объяснение слов через жесты и рисунки."
	}
]
